setup.py
docs/conf.py
montecarlo/__init__.py
montecarlo/cli.py
montecarlo/hyphotesis_testing.py
montecarlo_library-0.0.1.dist-info/METADATA
montecarlo_library-0.0.1.dist-info/WHEEL
montecarlo_library-0.0.1.dist-info/licenses/AUTHORS.rst
montecarlo_library-0.0.1.dist-info/licenses/LICENSE
montecarlo_library-0.0.1.dist-info/RECORD
