Metadata-Version: 2.1
Name: montecarlo_library
Version: 0.0.1
Summary: A small example package
Project-URL: Homepage, https://github.com/ErikaMelt/montecarlo_library
Project-URL: Bug Tracker, https://github.com/ErikaMelt/montecarlo_library
Author-email: Erika Ortiz <erikapaolaortiz@gmail.com>
License-File: AUTHORS.rst
License-File: LICENSE
Classifier: License :: OSI Approved :: MIT License
Classifier: Operating System :: OS Independent
Classifier: Programming Language :: Python :: 3
Requires-Python: >=3.7
